dtmf/__init__.py
dtmf/_analysis.py
dtmf/_detector.py
dtmf/_generator.py
dtmf/_info.py
dtmf/_parser.py
dtmf/model.py
dtmf-1.1.0.dist-info/LICENSE.md
dtmf-1.1.0.dist-info/METADATA
dtmf-1.1.0.dist-info/WHEEL
dtmf-1.1.0.dist-info/RECORD
