Metadata-Version: 2.1
Name: dtmf
Version: 1.1.0
Summary: Package for working with DTMF - a system for signaling over the voice band of a telephony system using multi-frequency tones.
Home-page: https://github.com/gdereese/dtmf
License: MIT
Keywords: dtmf,parser,telephony,voip
Author: Gary DeReese
Author-email: garydereese@sbcglobal.net
Requires-Python: >=3.10,<3.13
Classifier: License :: OSI Approved :: MIT License
Classifier: Programming Language :: Python :: 3
Classifier: Programming Language :: Python :: 3.10
Classifier: Programming Language :: Python :: 3.11
Classifier: Programming Language :: Python :: 3.12
Project-URL: Repository, https://github.com/gdereese/dtmf
